setup.py
swagger_server/__init__.py
swagger_server/__main__.py
swagger_server/encoder.py
swagger_server/util.py
swagger_server/controllers/__init__.py
swagger_server/controllers/label_store_functions.py
swagger_server/models/__init__.py
swagger_server/models/base_model_.py
swagger_server/models/label.py
swagger_server/test/__init__.py
swagger_server/test/test_label_store_functions_controller.py
swagger_server1.egg-info/PKG-INFO
swagger_server1.egg-info/SOURCES.txt
swagger_server1.egg-info/dependency_links.txt
swagger_server1.egg-info/requires.txt
swagger_server1.egg-info/top_level.txt