Metadata-Version: 1.0
Name: swagger-server1
Version: 1.0.0
Summary: Label Store Service
Home-page: UNKNOWN
Author: UNKNOWN
Author-email: UNKNOWN
License: UNKNOWN
Keywords: Swagger,Label Store Service
Platform: UNKNOWN
